[
  {
    "title": "nova-tv-online",
    "updated": "2025-09-02T20:53:40.774Z",
    "url": "https://cdn.stgledai.org:8082/hls/nova/index.m3u8?token=0f5bf63841843a4b0a9165bbd945a8990c39ebb0-c3b572c5640c438d270d91e9bda3de3c-1756856911-1756846111",
    "headers": "Referer: https://cdn.gledaitv.live/\nUser-Agent: Mozilla/5.0 (Windows NT 10.0; Win64; x64) AppleWebKit/537.36 (KHTML, like Gecko) Chrome/139.0.0.0 Safari/537.36"
  },
  {
    "title": "bnt-1-online",
    "updated": "2025-09-02T20:53:48.793Z",
    "url": "https://cdn.stgledai.org:8082/hls/bnt/index.m3u8?token=9c08aaa8fd9dae838aa6dfa61874e5d27319c1b2-b0a7988682d459c568c42a271bb2a159-1756856921-1756846121",
    "headers": "Referer: https://cdn.gledaitv.live/\nUser-Agent: Mozilla/5.0 (Windows NT 10.0; Win64; x64) AppleWebKit/537.36 (KHTML, like Gecko) Chrome/139.0.0.0 Safari/537.36"
  },
  {
    "title": "24-kitchen-online",
    "updated": "2025-09-02T20:53:56.827Z",
    "url": "https://cdn.stgledai.org:8082/hls/24kitchen/index.m3u8?token=de626e49049c8fb94de6b0180b1fd786187ac2f1-73c0f362ab2ee0b962283feac1f9ee39-1756856929-1756846129",
    "headers": "Referer: https://cdn.gledaitv.live/\nUser-Agent: Mozilla/5.0 (Windows NT 10.0; Win64; x64) AppleWebKit/537.36 (KHTML, like Gecko) Chrome/139.0.0.0 Safari/537.36"
  },
  {
    "title": "btv-online",
    "updated": "2025-09-02T20:54:04.353Z",
    "url": "https://cdn.stgledai.org:8082/hls/btv/index.m3u8?token=26776413047146defa13a0b036324292d4661cbc-b004decfc8ed82e8576b7cb8a40dca78-1756856937-1756846137",
    "headers": "Referer: https://cdn.gledaitv.live/\nUser-Agent: Mozilla/5.0 (Windows NT 10.0; Win64; x64) AppleWebKit/537.36 (KHTML, like Gecko) Chrome/139.0.0.0 Safari/537.36"
  }
]