[
  {
    "title": "nova-tv-online",
    "updated": "2025-08-31T20:10:18.952Z",
    "url": "https://cdn.stgledai.org:8082/hls/nova/index.m3u8?token=962106f79165c1031077cd6fd702cbe1843fda46-ef48e4950f9cef37bf6940bdd146d22f-1756681509-1756670709",
    "headers": "Referer: https://cdn.gledaitv.live/\nUser-Agent: Mozilla/5.0 (Windows NT 10.0; Win64; x64) AppleWebKit/537.36 (KHTML, like Gecko) Chrome/139.0.0.0 Safari/537.36"
  },
  {
    "title": "bnt-1-online",
    "updated": "2025-08-31T20:10:27.548Z",
    "url": "https://cdn.stgledai.org:8082/hls/bnt/index.m3u8?token=41402cca9200ec9f10e4ea870002cedd6a7afa99-a4cf3f85f6a7cff5bdad0e2add369a38-1756681519-1756670719",
    "headers": "Referer: https://cdn.gledaitv.live/\nUser-Agent: Mozilla/5.0 (Windows NT 10.0; Win64; x64) AppleWebKit/537.36 (KHTML, like Gecko) Chrome/139.0.0.0 Safari/537.36"
  },
  {
    "title": "24-kitchen-online",
    "updated": "2025-08-31T20:10:36.091Z",
    "url": "https://cdn.stgledai.org:8082/hls/24kitchen/index.m3u8?token=1bf0bd3d7a2897bda86d746d4e892aeb6a1bb3c3-50268a1cb445e6a53d6a81ca9fa5a72d-1756681527-1756670727",
    "headers": "Referer: https://cdn.gledaitv.live/\nUser-Agent: Mozilla/5.0 (Windows NT 10.0; Win64; x64) AppleWebKit/537.36 (KHTML, like Gecko) Chrome/139.0.0.0 Safari/537.36"
  },
  {
    "title": "btv-online",
    "updated": "2025-08-31T20:10:44.715Z",
    "url": "https://cdn.stgledai.org:8082/hls/btv/index.m3u8?token=0733e6e9303136bb8f7f804108cda7133142264c-f30298bea1cfe56d567324f615b44857-1756681536-1756670736",
    "headers": "Referer: https://cdn.gledaitv.live/\nUser-Agent: Mozilla/5.0 (Windows NT 10.0; Win64; x64) AppleWebKit/537.36 (KHTML, like Gecko) Chrome/139.0.0.0 Safari/537.36"
  }
]