[
  {
    "title": "nova-tv-online",
    "updated": "2025-09-02T11:09:03.177Z",
    "url": "https://cdn.stgledai.org:8082/hls/nova/index.m3u8?token=26be351bf23cdb30a2dde03c5019754cb8f49630-eb33bca15d469d42485d273ae773ae92-1756821832-1756811032",
    "headers": "Referer: https://cdn.gledaitv.live/\nUser-Agent: Mozilla/5.0 (Windows NT 10.0; Win64; x64) AppleWebKit/537.36 (KHTML, like Gecko) Chrome/139.0.0.0 Safari/537.36"
  },
  {
    "title": "bnt-1-online",
    "updated": "2025-09-02T11:09:11.546Z",
    "url": "https://cdn.stgledai.org:8082/hls/bnt/index.m3u8?token=249d343401c6efc7308da03b2b8758f5e4b3831e-cd5e529ae67d9dc2e72d844715fd78b7-1756821843-1756811043",
    "headers": "Referer: https://cdn.gledaitv.live/\nUser-Agent: Mozilla/5.0 (Windows NT 10.0; Win64; x64) AppleWebKit/537.36 (KHTML, like Gecko) Chrome/139.0.0.0 Safari/537.36"
  },
  {
    "title": "24-kitchen-online",
    "updated": "2025-09-02T11:09:19.626Z",
    "url": "https://cdn.stgledai.org:8082/hls/24kitchen/index.m3u8?token=8060b2b3e34efba317399f2005b947607101a398-037a4cb8266e485b2151eed165449086-1756821851-1756811051",
    "headers": "Referer: https://cdn.gledaitv.live/\nUser-Agent: Mozilla/5.0 (Windows NT 10.0; Win64; x64) AppleWebKit/537.36 (KHTML, like Gecko) Chrome/139.0.0.0 Safari/537.36"
  },
  {
    "title": "btv-online",
    "updated": "2025-09-02T11:09:27.799Z",
    "url": "https://cdn.stgledai.org:8082/hls/btv/index.m3u8?token=d26e68b218ed7e8c110159d9d15254d09863c5b6-f1b6defbf780a9714abfed32b0c69463-1756821859-1756811059",
    "headers": "Referer: https://cdn.gledaitv.live/\nUser-Agent: Mozilla/5.0 (Windows NT 10.0; Win64; x64) AppleWebKit/537.36 (KHTML, like Gecko) Chrome/139.0.0.0 Safari/537.36"
  }
]