[
  {
    "title": "nova-tv-online",
    "updated": "2025-09-20T17:42:34.026Z",
    "url": "https://cdn.stgledai.org:8082/hls/nova/index.m3u8?token=4662a929e836b4da01c2f5d658b30c5b74c9ab38-af6d63f4dfae77d522f5f7b47927cd45-1758400644-1758389844",
    "headers": "Referer: https://cdn.gledaitv.live/\nUser-Agent: Mozilla/5.0 (Windows NT 10.0; Win64; x64) AppleWebKit/537.36 (KHTML, like Gecko) Chrome/139.0.0.0 Safari/537.36"
  },
  {
    "title": "bnt-1-online",
    "updated": "2025-09-20T17:42:42.081Z",
    "url": "https://cdn.stgledai.org:8082/hls/bnt/index.m3u8?token=de98755be80ac42988940ef152497c71ec01f480-c2fe55f27df83a97eeaf99062beedfbb-1758400654-1758389854",
    "headers": "Referer: https://cdn.gledaitv.live/\nUser-Agent: Mozilla/5.0 (Windows NT 10.0; Win64; x64) AppleWebKit/537.36 (KHTML, like Gecko) Chrome/139.0.0.0 Safari/537.36"
  },
  {
    "title": "24-kitchen-online",
    "updated": "2025-09-20T17:42:50.129Z",
    "url": "https://cdn.stgledai.org:8082/hls/24kitchen/index.m3u8?token=d507dcc02bf5441400ac2f497eb400c5c82cddbd-fa7206883eca3bd85768671ba93f48a7-1758400662-1758389862",
    "headers": "Referer: https://cdn.gledaitv.live/\nUser-Agent: Mozilla/5.0 (Windows NT 10.0; Win64; x64) AppleWebKit/537.36 (KHTML, like Gecko) Chrome/139.0.0.0 Safari/537.36"
  },
  {
    "title": "btv-online",
    "updated": "2025-09-20T17:42:59.291Z",
    "url": "https://cdn.stgledai.org:8082/hls/btv/index.m3u8?token=2f73d51c60b4a94d92aa546fc964d79f33574468-50c4f7af026d3dc21aecc78852c39c0d-1758400670-1758389870",
    "headers": "Referer: https://cdn.gledaitv.live/\nUser-Agent: Mozilla/5.0 (Windows NT 10.0; Win64; x64) AppleWebKit/537.36 (KHTML, like Gecko) Chrome/139.0.0.0 Safari/537.36"
  }
]